odoo/addons/account_statement_import_txt_xlsx/README.rst
odoo/addons/account_statement_import_txt_xlsx/__init__.py
odoo/addons/account_statement_import_txt_xlsx/__manifest__.py
odoo/addons/account_statement_import_txt_xlsx/data/map_data.xml
odoo/addons/account_statement_import_txt_xlsx/i18n/account_bank_statement_import_txt_xlsx.pot
odoo/addons/account_statement_import_txt_xlsx/i18n/account_statement_import_txt_xlsx.pot
odoo/addons/account_statement_import_txt_xlsx/i18n/es.po
odoo/addons/account_statement_import_txt_xlsx/i18n/es_AR.po
odoo/addons/account_statement_import_txt_xlsx/i18n/it.po
odoo/addons/account_statement_import_txt_xlsx/i18n/nl.po
odoo/addons/account_statement_import_txt_xlsx/i18n/pt.po
odoo/addons/account_statement_import_txt_xlsx/i18n/zh_CN.po
odoo/addons/account_statement_import_txt_xlsx/migrations/15.0.1.1.0/pre-migrate.py
odoo/addons/account_statement_import_txt_xlsx/models/__init__.py
odoo/addons/account_statement_import_txt_xlsx/models/account_journal.py
odoo/addons/account_statement_import_txt_xlsx/models/account_statement_import.py
odoo/addons/account_statement_import_txt_xlsx/models/account_statement_import_sheet_mapping.py
odoo/addons/account_statement_import_txt_xlsx/models/account_statement_import_sheet_parser.py
odoo/addons/account_statement_import_txt_xlsx/readme/CONFIGURE.rst
odoo/addons/account_statement_import_txt_xlsx/readme/CONTRIBUTORS.rst
odoo/addons/account_statement_import_txt_xlsx/readme/DESCRIPTION.rst
odoo/addons/account_statement_import_txt_xlsx/readme/HISTORY.rst
odoo/addons/account_statement_import_txt_xlsx/readme/USAGE.rst
odoo/addons/account_statement_import_txt_xlsx/security/ir.model.access.csv
odoo/addons/account_statement_import_txt_xlsx/static/description/icon.png
odoo/addons/account_statement_import_txt_xlsx/static/description/index.html
odoo/addons/account_statement_import_txt_xlsx/tests/__init__.py
odoo/addons/account_statement_import_txt_xlsx/tests/test_account_statement_import_txt_xlsx.py
odoo_addon_account_statement_import_txt_xlsx-15.0.2.1.2.dist-info/METADATA
odoo_addon_account_statement_import_txt_xlsx-15.0.2.1.2.dist-info/WHEEL
odoo_addon_account_statement_import_txt_xlsx-15.0.2.1.2.dist-info/top_level.txt
odoo_addon_account_statement_import_txt_xlsx-15.0.2.1.2.dist-info/RECORD
