Metadata-Version: 2.1
Name: odoo-addon-account_statement_import_txt_xlsx
Version: 15.0.2.1.2
Summary: Import TXT/CSV or XLSX files as Bank Statements in Odoo
Home-page: https://github.com/OCA/bank-statement-import
Author: ForgeFlow, CorporateHub, Odoo Community Association (OCA)
Author-email: support@odoo-community.org
License: AGPL-3
Classifier: Programming Language :: Python
Classifier: Framework :: Odoo
Classifier: Framework :: Odoo :: 15.0
Classifier: License :: OSI Approved :: GNU Affero General Public License v3
Requires-Python: >=3.8
Requires-Dist: chardet
Requires-Dist: odoo-addon-account-statement-import<15.1dev,>=15.0dev
Requires-Dist: odoo-addon-multi-step-wizard<15.1dev,>=15.0dev
Requires-Dist: odoo-addon-web-widget-dropdown-dynamic<15.1dev,>=15.0dev
Requires-Dist: odoo<15.1dev,>=15.0a
Requires-Dist: xlrd
